{"v":"5.8.1","fr":29.97,"ip":0,"op":90,"w":1000,"h":1000,"nm":"Untitled-2-81","assets":[{"id":"comp_0","nm":"Pre-comp 1","fr":29.97,"layers":[{"ind":1,"ty":4,"nm":"Layer 2 Outlines","sr":1,"ks":{"o":{"a":0,"k":100},"r":{"a":0,"k":0},"p":{"a":0,"k":[471.017,584.014,0],"l":2},"a":{"a":0,"k":[319.222,84.96,0],"l":2},"s":{"a":0,"k":[100,100,100],"l":2}},"ao":0,"shapes":[{"ty":"gr","it":[{"ty":"gr","it":[{"ind":0,"ty":"sh","ks":{"a":0,"k":{"i":[[0,-8.126],[7.89,0],[0,8.126],[-7.891,0]],"o":[[0,8.126],[-7.891,0],[0,-8.126],[7.89,0]],"v":[[14.281,0],[0,14.707],[-14.281,0],[0,-14.707]],"c":true}},"nm":"Path 1"},{"ty":"fl","c":{"a":0,"k":[0.248,0.214,0.218,1]},"o":{"a":0,"k":100},"r":1,"nm":"Fill 1"},{"ty":"tr","p":{"a":0,"k":[556.077,84.817]},"a":{"a":0,"k":[0,0]},"s":{"a":0,"k":[100,100]},"r":{"a":0,"k":0},"o":{"a":0,"k":100},"sk":{"a":0,"k":0},"sa":{"a":0,"k":0},"nm":"Transform"}],"nm":"Group 1"},{"ty":"gr","it":[{"ind":0,"ty":"sh","ks":{"a":0,"k":{"i":[[0.161,-1.82],[0,0],[0,0],[1.646,-3.268],[0,0],[0,0],[2.691,-2.399],[0,0],[0,0],[3.455,-1.158],[0,0],[0,0],[1.807,0],[1.767,0.166],[0,0],[0,0],[3.173,1.696],[0,0],[0,0],[2.33,2.771],[0,0],[0,0],[1.125,3.557],[0,0],[0,0],[0,1.861],[-0.161,1.82],[0,0],[0,0],[-1.647,3.268],[0,0],[0,0],[-2.691,2.398],[0,0],[0,0],[-3.454,1.159],[0,0],[0,0],[-1.807,0],[-1.767,-0.165],[0,0],[0,0],[-3.173,-1.696],[0,0],[0,0],[-2.329,-2.771],[0,0],[0,0],[-1.125,-3.557],[0,0],[0,0],[0,-1.861]],"o":[[0,0],[0,0],[-1.085,3.558],[0,0],[0,0],[-2.329,2.771],[0,0],[0,0],[-3.134,1.696],[0,0],[0,0],[-1.767,0.166],[-1.807,0],[0,0],[0,0],[-3.454,-1.117],[0,0],[0,0],[-2.691,-2.399],[0,0],[0,0],[-1.647,-3.227],[0,0],[0,0],[-0.161,-1.82],[0,-1.861],[0,0],[0,0],[1.085,-3.557],[0,0],[0,0],[2.33,-2.771],[0,0],[0,0],[3.133,-1.696],[0,0],[0,0],[1.767,-0.165],[1.807,0],[0,0],[0,0],[3.455,1.117],[0,0],[0,0],[2.691,2.398],[0,0],[0,0],[1.646,3.226],[0,0],[0,0],[0.161,1.82],[0,1.861]],"v":[[65.071,5.543],[27.756,5.543],[62.42,19.896],[58.363,30.155],[22.413,15.264],[49.847,43.516],[42.256,51.334],[15.786,24.074],[30.447,59.524],[20.565,63.826],[5.382,27.135],[5.382,67.011],[0,67.259],[-5.382,67.011],[-5.382,28.583],[-19.321,64.281],[-29.282,60.103],[-14.822,23.081],[-42.256,51.334],[-49.848,43.516],[-23.377,16.256],[-57.801,31.355],[-61.978,21.179],[-26.35,5.543],[-65.071,5.543],[-65.312,0],[-65.071,-5.543],[-27.756,-5.543],[-62.42,-19.897],[-58.363,-30.155],[-22.413,-15.264],[-49.848,-43.516],[-42.256,-51.333],[-15.786,-24.074],[-30.447,-59.524],[-20.566,-63.826],[-5.382,-27.135],[-5.382,-67.011],[0,-67.259],[5.382,-67.011],[5.382,-28.583],[19.32,-64.281],[29.282,-60.103],[14.822,-23.082],[42.256,-51.333],[49.847,-43.516],[23.377,-16.256],[57.801,-31.354],[61.978,-21.179],[26.35,-5.543],[65.071,-5.543],[65.312,0]],"c":true}},"nm":"Path 1"},{"ty":"fl","c":{"a":0,"k":[0.888,0.884,0.863,1]},"o":{"a":0,"k":100},"r":1,"nm":"Fill 1"},{"ty":"tr","p":{"a":0,"k":[556.076,84.817]},"a":{"a":0,"k":[0,0]},"s":{"a":0,"k":[100,100]},"r":{"a":1,"k":[{"i":{"x":[0.833],"y":[0.833]},"o":{"x":[0.167],"y":[0.167]},"t":0,"s":[720]},{"t":89,"s":[0]}]},"o":{"a":0,"k":100},"sk":{"a":0,"k":0},"sa":{"a":0,"k":0},"nm":"Transform"}],"nm":"Group 2"},{"ty":"gr","it":[{"ind":0,"ty":"sh","ks":{"a":0,"k":{"i":[[0,-37.161],[36.084,0],[0,37.16],[-36.085,0]],"o":[[0,37.16],[-36.085,0],[0,-37.161],[36.084,0]],"v":[[65.312,0],[0,67.259],[-65.312,0],[0,-67.259]],"c":true}},"nm":"Path 1"},{"ty":"fl","c":{"a":0,"k":[0.149,0.11,0.114,1]},"o":{"a":0,"k":100},"r":1,"nm":"Fill 1"},{"ty":"tr","p":{"a":0,"k":[556.076,84.817]},"a":{"a":0,"k":[0,0]},"s":{"a":0,"k":[100,100]},"r":{"a":0,"k":0},"o":{"a":0,"k":100},"sk":{"a":0,"k":0},"sa":{"a":0,"k":0},"nm":"Transform"}],"nm":"Group 3"},{"ty":"gr","it":[{"ind":0,"ty":"sh","ks":{"a":0,"k":{"i":[[0,-46.723],[45.37,0],[0,46.723],[-45.371,0]],"o":[[0,46.723],[-45.371,0],[0,-46.723],[45.37,0]],"v":[[82.119,0],[0,84.567],[-82.118,0],[0,-84.567]],"c":true}},"nm":"Path 1"},{"ty":"fl","c":{"a":0,"k":[0.248,0.214,0.218,1]},"o":{"a":0,"k":100},"r":1,"nm":"Fill 1"},{"ty":"tr","p":{"a":0,"k":[556.076,84.817]},"a":{"a":0,"k":[0,0]},"s":{"a":0,"k":[100,100]},"r":{"a":0,"k":0},"o":{"a":0,"k":100},"sk":{"a":0,"k":0},"sa":{"a":0,"k":0},"nm":"Transform"}],"nm":"Group 4"},{"ty":"tr","p":{"a":0,"k":[556.076,84.817]},"a":{"a":0,"k":[556.076,84.817]},"s":{"a":0,"k":[100,100]},"r":{"a":0,"k":0},"o":{"a":0,"k":100},"sk":{"a":0,"k":0},"sa":{"a":0,"k":0},"nm":"Transform"}],"nm":"Group 9"},{"ty":"gr","it":[{"ty":"gr","it":[{"ind":0,"ty":"sh","ks":{"a":0,"k":{"i":[[0,-8.126],[7.89,0],[0,8.126],[-7.891,0]],"o":[[0,8.126],[-7.891,0],[0,-8.126],[7.89,0]],"v":[[14.281,0],[0,14.707],[-14.281,0],[0,-14.707]],"c":true}},"nm":"Path 1"},{"ty":"fl","c":{"a":0,"k":[0.248,0.214,0.218,1]},"o":{"a":0,"k":100},"r":1,"nm":"Fill 1"},{"ty":"tr","p":{"a":0,"k":[82.369,85.103]},"a":{"a":0,"k":[0,0]},"s":{"a":0,"k":[100,100]},"r":{"a":0,"k":0},"o":{"a":0,"k":100},"sk":{"a":0,"k":0},"sa":{"a":0,"k":0},"nm":"Transform"}],"nm":"Group 5"},{"ty":"gr","it":[{"ind":0,"ty":"sh","ks":{"a":0,"k":{"i":[[0.161,-1.82],[0,0],[0,0],[1.647,-3.268],[0,0],[0,0],[2.691,-2.399],[0,0],[0,0],[3.454,-1.158],[0,0],[0,0],[1.807,0],[1.767,0.166],[0,0],[0,0],[3.174,1.696],[0,0],[0,0],[2.329,2.771],[0,0],[0,0],[1.125,3.557],[0,0],[0,0],[0,1.861],[-0.161,1.82],[0,0],[0,0],[-1.647,3.268],[0,0],[0,0],[-2.691,2.398],[0,0],[0,0],[-3.454,1.159],[0,0],[0,0],[-1.807,0],[-1.767,-0.165],[0,0],[0,0],[-3.173,-1.696],[0,0],[0,0],[-2.329,-2.771],[0,0],[0,0],[-1.125,-3.557],[0,0],[0,0],[0,-1.861]],"o":[[0,0],[0,0],[-1.084,3.558],[0,0],[0,0],[-2.329,2.771],[0,0],[0,0],[-3.133,1.696],[0,0],[0,0],[-1.767,0.166],[-1.807,0],[0,0],[0,0],[-3.454,-1.117],[0,0],[0,0],[-2.691,-2.399],[0,0],[0,0],[-1.646,-3.227],[0,0],[0,0],[-0.161,-1.82],[0,-1.861],[0,0],[0,0],[1.085,-3.557],[0,0],[0,0],[2.329,-2.771],[0,0],[0,0],[3.133,-1.696],[0,0],[0,0],[1.767,-0.165],[1.807,0],[0,0],[0,0],[3.454,1.117],[0,0],[0,0],[2.691,2.398],[0,0],[0,0],[1.647,3.226],[0,0],[0,0],[0.161,1.82],[0,1.861]],"v":[[65.071,5.543],[27.756,5.543],[62.42,19.896],[58.363,30.155],[22.413,15.264],[49.847,43.516],[42.256,51.334],[15.786,24.074],[30.447,59.524],[20.566,63.826],[5.382,27.135],[5.382,67.011],[0,67.259],[-5.382,67.011],[-5.382,28.583],[-19.321,64.281],[-29.282,60.103],[-14.822,23.081],[-42.256,51.334],[-49.847,43.516],[-23.377,16.256],[-57.801,31.355],[-61.978,21.179],[-26.35,5.543],[-65.071,5.543],[-65.312,0],[-65.071,-5.543],[-27.756,-5.543],[-62.42,-19.897],[-58.363,-30.155],[-22.413,-15.264],[-49.847,-43.516],[-42.256,-51.333],[-15.786,-24.074],[-30.447,-59.524],[-20.566,-63.826],[-5.382,-27.135],[-5.382,-67.011],[0,-67.259],[5.382,-67.011],[5.382,-28.583],[19.321,-64.281],[29.282,-60.103],[14.822,-23.082],[42.256,-51.333],[49.847,-43.516],[23.377,-16.256],[57.801,-31.354],[61.978,-21.179],[26.35,-5.543],[65.071,-5.543],[65.312,0]],"c":true}},"nm":"Path 1"},{"ty":"fl","c":{"a":0,"k":[0.888,0.884,0.863,1]},"o":{"a":0,"k":100},"r":1,"nm":"Fill 1"},{"ty":"tr","p":{"a":0,"k":[82.369,85.103]},"a":{"a":0,"k":[0,0]},"s":{"a":0,"k":[100,100]},"r":{"a":1,"k":[{"i":{"x":[0.833],"y":[0.833]},"o":{"x":[0.167],"y":[0.167]},"t":0,"s":[720]},{"t":89,"s":[0]}]},"o":{"a":0,"k":100},"sk":{"a":0,"k":0},"sa":{"a":0,"k":0},"nm":"Transform"}],"nm":"Group 6"},{"ty":"gr","it":[{"ind":0,"ty":"sh","ks":{"a":0,"k":{"i":[[0,-37.161],[36.085,0],[0,37.16],[-36.085,0]],"o":[[0,37.16],[-36.085,0],[0,-37.161],[36.085,0]],"v":[[65.312,0],[0,67.259],[-65.312,0],[0,-67.259]],"c":true}},"nm":"Path 1"},{"ty":"fl","c":{"a":0,"k":[0.149,0.11,0.114,1]},"o":{"a":0,"k":100},"r":1,"nm":"Fill 1"},{"ty":"tr","p":{"a":0,"k":[82.369,85.103]},"a":{"a":0,"k":[0,0]},"s":{"a":0,"k":[100,100]},"r":{"a":0,"k":0},"o":{"a":0,"k":100},"sk":{"a":0,"k":0},"sa":{"a":0,"k":0},"nm":"Transform"}],"nm":"Group 7"},{"ty":"gr","it":[{"ind":0,"ty":"sh","ks":{"a":0,"k":{"i":[[0,-46.723],[45.37,0],[0,46.723],[-45.371,0]],"o":[[0,46.723],[-45.371,0],[0,-46.723],[45.37,0]],"v":[[82.118,0],[0.001,84.567],[-82.118,0],[0.001,-84.567]],"c":true}},"nm":"Path 1"},{"ty":"fl","c":{"a":0,"k":[0.248,0.214,0.218,1]},"o":{"a":0,"k":100},"r":1,"nm":"Fill 1"},{"ty":"tr","p":{"a":0,"k":[82.368,85.103]},"a":{"a":0,"k":[0,0]},"s":{"a":0,"k":[100,100]},"r":{"a":0,"k":0},"o":{"a":0,"k":100},"sk":{"a":0,"k":0},"sa":{"a":0,"k":0},"nm":"Transform"}],"nm":"Group 8"},{"ty":"tr","p":{"a":0,"k":[82.368,85.103]},"a":{"a":0,"k":[82.368,85.103]},"s":{"a":0,"k":[100,100]},"r":{"a":0,"k":0},"o":{"a":0,"k":100},"sk":{"a":0,"k":0},"sa":{"a":0,"k":0},"nm":"Transform"}],"nm":"Group 10"}],"ip":0,"op":90,"st":0},{"ind":2,"ty":4,"nm":"Layer 1 Outlines","sr":1,"ks":{"o":{"a":0,"k":100},"r":{"a":0,"k":0},"p":{"a":0,"k":[500,458.74,0],"l":2},"a":{"a":0,"k":[430.25,125.935,0],"l":2},"s":{"a":0,"k":[100,100,100],"l":2}},"ao":0,"shapes":[{"ty":"gr","it":[{"ind":0,"ty":"sh","ks":{"a":0,"k":{"i":[[3.464,-0.024],[0,0],[0.024,3.568],[-3.464,0.025],[0,0],[-0.025,-3.567]],"o":[[0,0],[-3.464,0.025],[-0.024,-3.567],[0,0],[3.464,-0.025],[0.024,3.567]],"v":[[74.375,5.923],[-74.287,6.995],[-80.603,0.579],[-74.374,-5.924],[74.288,-6.994],[80.603,-0.58]],"c":true}},"nm":"Path 1"},{"ty":"fl","c":{"a":0,"k":[1,1,1,1]},"o":{"a":0,"k":100},"r":1,"nm":"Fill 1"},{"ty":"tr","p":{"a":0,"k":[180.898,111.523]},"a":{"a":0,"k":[0,0]},"s":{"a":0,"k":[100,100]},"r":{"a":0,"k":0},"o":{"a":0,"k":100},"sk":{"a":0,"k":0},"sa":{"a":0,"k":0},"nm":"Transform"}],"nm":"Group 1"},{"ty":"gr","it":[{"ind":0,"ty":"sh","ks":{"a":0,"k":{"i":[[3.464,0],[0,0],[0,3.567],[-3.464,0],[0,0],[0,-3.568]],"o":[[0,0],[-3.464,0],[0,-3.568],[0,0],[3.464,0],[0,3.567]],"v":[[74.333,6.459],[-74.333,6.459],[-80.605,0.001],[-74.333,-6.459],[74.333,-6.459],[80.605,0.001]],"c":true}},"nm":"Path 1"},{"ty":"fl","c":{"a":0,"k":[1,1,1,1]},"o":{"a":0,"k":100},"r":1,"nm":"Fill 1"},{"ty":"tr","p":{"a":0,"k":[360.034,225.893]},"a":{"a":0,"k":[0,0]},"s":{"a":0,"k":[100,100]},"r":{"a":0,"k":0},"o":{"a":0,"k":100},"sk":{"a":0,"k":0},"sa":{"a":0,"k":0},"nm":"Transform"}],"nm":"Group 2"},{"ty":"gr","it":[{"ind":0,"ty":"sh","ks":{"a":0,"k":{"i":[[3.464,0],[0,0],[0,3.567],[-3.464,0],[0,0],[0,-3.568]],"o":[[0,0],[-3.464,0],[0,-3.568],[0,0],[3.464,0],[0,3.567]],"v":[[5.306,6.459],[-5.305,6.459],[-11.578,0.001],[-5.305,-6.459],[5.306,-6.459],[11.578,0.001]],"c":true}},"nm":"Path 1"},{"ty":"fl","c":{"a":0,"k":[1,1,1,1]},"o":{"a":0,"k":100},"r":1,"nm":"Fill 1"},{"ty":"tr","p":{"a":0,"k":[459.767,225.893]},"a":{"a":0,"k":[0,0]},"s":{"a":0,"k":[100,100]},"r":{"a":0,"k":0},"o":{"a":0,"k":100},"sk":{"a":0,"k":0},"sa":{"a":0,"k":0},"nm":"Transform"}],"nm":"Group 3"},{"ty":"gr","it":[{"ind":0,"ty":"sh","ks":{"a":0,"k":{"i":[[0,-6.114],[0,0],[5.937,0],[0,0],[0,6.114],[0,0],[-5.937,0],[0,0]],"o":[[0,0],[0,6.114],[0,0],[-5.937,0],[0,0],[0,-6.114],[0,0],[5.937,0]],"v":[[20.424,-9.964],[20.424,9.963],[9.674,21.033],[-9.676,21.033],[-20.424,9.963],[-20.424,-9.964],[-9.676,-21.033],[9.674,-21.033]],"c":true}},"nm":"Path 1"},{"ty":"fl","c":{"a":0,"k":[1,0.333,0.237,1]},"o":{"a":0,"k":100},"r":1,"nm":"Fill 1"},{"ty":"tr","p":{"a":0,"k":[723.729,122.761]},"a":{"a":0,"k":[0,0]},"s":{"a":0,"k":[100,100]},"r":{"a":0,"k":0},"o":{"a":0,"k":100},"sk":{"a":0,"k":0},"sa":{"a":0,"k":0},"nm":"Transform"}],"nm":"Group 4"},{"ty":"gr","it":[{"ind":0,"ty":"sh","ks":{"a":0,"k":{"i":[[-1.076,-2.214],[1.076,0],[0,0],[0,-4.427],[-0.716,-1.107],[0,3.136],[-4.12,0],[0,0]],"o":[[-0.897,-0.369],[0,0],[-4.121,0],[0,1.293],[-2.508,-1.107],[0,-4.243],[0,0],[2.867,0]],"v":[[25.979,-3.598],[22.931,-4.151],[-15.229,-4.151],[-22.754,3.782],[-21.68,7.473],[-25.979,0.462],[-18.455,-7.473],[19.707,-7.473]],"c":true}},"nm":"Path 1"},{"ty":"fl","c":{"a":0,"k":[0.954,0.291,0.212,1]},"o":{"a":0,"k":100},"r":1,"nm":"Fill 1"},{"ty":"tr","p":{"a":0,"k":[627.204,111.967]},"a":{"a":0,"k":[0,0]},"s":{"a":0,"k":[100,100]},"r":{"a":0,"k":0},"o":{"a":0,"k":100},"sk":{"a":0,"k":0},"sa":{"a":0,"k":0},"nm":"Transform"}],"nm":"Group 5"},{"ty":"gr","it":[{"ind":0,"ty":"sh","ks":{"a":0,"k":{"i":[[0,-4.336],[4.315,0],[0,0],[0,4.335],[-4.21,0],[0,0]],"o":[[0,4.335],[0,0],[-4.21,0],[0,-4.336],[0,0],[4.315,0]],"v":[[26.734,0],[19.051,7.913],[-19.051,7.913],[-26.734,0],[-19.051,-7.913],[19.051,-7.913]],"c":true}},"nm":"Path 1"},{"ty":"fl","c":{"a":0,"k":[1,0.333,0.237,1]},"o":{"a":0,"k":100},"r":1,"nm":"Fill 1"},{"ty":"tr","p":{"a":0,"k":[627.881,112.429]},"a":{"a":0,"k":[0,0]},"s":{"a":0,"k":[100,100]},"r":{"a":0,"k":0},"o":{"a":0,"k":100},"sk":{"a":0,"k":0},"sa":{"a":0,"k":0},"nm":"Transform"}],"nm":"Group 6"},{"ty":"gr","it":[{"ind":0,"ty":"sh","ks":{"a":0,"k":{"i":[[-1.076,-2.214],[1.075,0],[0,0],[0,-4.427],[-0.716,-1.107],[0,3.136],[-4.121,0],[0,0]],"o":[[-0.897,-0.369],[0,0],[-4.12,0],[0,1.293],[-2.508,-1.107],[0,-4.243],[0,0],[2.867,0]],"v":[[25.979,-3.598],[22.932,-4.151],[-15.229,-4.151],[-22.754,3.782],[-21.68,7.473],[-25.979,0.462],[-18.453,-7.473],[19.707,-7.473]],"c":true}},"nm":"Path 1"},{"ty":"fl","c":{"a":0,"k":[0.954,0.291,0.212,1]},"o":{"a":0,"k":100},"r":1,"nm":"Fill 1"},{"ty":"tr","p":{"a":0,"k":[468.782,111.967]},"a":{"a":0,"k":[0,0]},"s":{"a":0,"k":[100,100]},"r":{"a":0,"k":0},"o":{"a":0,"k":100},"sk":{"a":0,"k":0},"sa":{"a":0,"k":0},"nm":"Transform"}],"nm":"Group 7"},{"ty":"gr","it":[{"ind":0,"ty":"sh","ks":{"a":0,"k":{"i":[[0,-4.336],[4.315,0],[0,0],[0,4.335],[-4.21,0],[0,0]],"o":[[0,4.335],[0,0],[-4.21,0],[0,-4.336],[0,0],[4.315,0]],"v":[[26.734,0],[19.051,7.913],[-19.051,7.913],[-26.734,0],[-19.051,-7.913],[19.051,-7.913]],"c":true}},"nm":"Path 1"},{"ty":"fl","c":{"a":0,"k":[1,0.333,0.237,1]},"o":{"a":0,"k":100},"r":1,"nm":"Fill 1"},{"ty":"tr","p":{"a":0,"k":[469.459,112.429]},"a":{"a":0,"k":[0,0]},"s":{"a":0,"k":[100,100]},"r":{"a":0,"k":0},"o":{"a":0,"k":100},"sk":{"a":0,"k":0},"sa":{"a":0,"k":0},"nm":"Transform"}],"nm":"Group 8"},{"ty":"gr","it":[{"ind":0,"ty":"sh","ks":{"a":0,"k":{"i":[[0,-2.952],[0,0],[0,0],[0.716,3.137],[-0.716,0],[0,0],[0,0],[0.357,1.107],[0,0]],"o":[[0,0],[0,0],[-3.225,0],[0.716,0.185],[0,0],[0,0],[0,-1.107],[0,0],[0.895,2.583]],"v":[[12.093,-12.73],[12.093,21.033],[-5.285,21.033],[-12.093,15.683],[-10.123,16.052],[7.255,16.052],[7.255,-17.712],[6.898,-21.033],[10.839,-21.033]],"c":true}},"nm":"Path 1"},{"ty":"fl","c":{"a":0,"k":[0.461,0.353,0.681,1]},"o":{"a":0,"k":100},"r":1,"nm":"Fill 1"},{"ty":"tr","p":{"a":0,"k":[848.157,125.897]},"a":{"a":0,"k":[0,0]},"s":{"a":0,"k":[100,100]},"r":{"a":0,"k":0},"o":{"a":0,"k":100},"sk":{"a":0,"k":0},"sa":{"a":0,"k":0},"nm":"Transform"}],"nm":"Group 9"},{"ty":"gr","it":[{"ind":0,"ty":"sh","ks":{"a":0,"k":{"i":[[0,-2.952],[0,0],[0,0],[0,4.243],[0,0],[-3.942,0],[0,0]],"o":[[0,0],[0,0],[-3.942,0],[0,0],[0,-4.059],[0,0],[0.895,2.583]],"v":[[12.273,-12.73],[12.273,21.033],[-5.106,21.033],[-12.273,13.654],[-12.273,-13.653],[-5.106,-21.033],[11.018,-21.033]],"c":true}},"nm":"Path 1"},{"ty":"fl","c":{"a":0,"k":[0.548,0.453,0.724,1]},"o":{"a":0,"k":100},"r":1,"nm":"Fill 1"},{"ty":"tr","p":{"a":0,"k":[847.977,125.897]},"a":{"a":0,"k":[0,0]},"s":{"a":0,"k":[100,100]},"r":{"a":0,"k":0},"o":{"a":0,"k":100},"sk":{"a":0,"k":0},"sa":{"a":0,"k":0},"nm":"Transform"}],"nm":"Group 10"},{"ty":"gr","it":[{"ind":0,"ty":"sh","ks":{"a":0,"k":{"i":[[-3.045,0.184],[27.221,0],[0,0],[0,0],[-0.358,0.922],[0,0],[-7.2,20.261]],"o":[[-4.93,25.386],[0,0],[0,0],[0,-1.107],[0,0],[24.431,0],[2.686,-0.37]],"v":[[39.146,-22.694],[-14.96,22.694],[-39.146,22.694],[-39.146,17.527],[-38.788,14.576],[-21.052,14.576],[30.547,-21.955]],"c":true}},"nm":"Path 1"},{"ty":"fl","c":{"a":0,"k":[0.925,0.738,0.168,1]},"o":{"a":0,"k":100},"r":1,"nm":"Fill 1"},{"ty":"tr","p":{"a":0,"k":[39.421,118.517]},"a":{"a":0,"k":[0,0]},"s":{"a":0,"k":[100,100]},"r":{"a":0,"k":0},"o":{"a":0,"k":100},"sk":{"a":0,"k":0},"sa":{"a":0,"k":0},"nm":"Transform"}],"nm":"Group 11"},{"ty":"gr","it":[{"ind":0,"ty":"sh","ks":{"a":0,"k":{"i":[[-46.94,2.767],[27.221,0],[0,0],[0,0],[-3.045,3.506]],"o":[[-4.93,25.386],[0,0],[0,0],[0,-4.612],[7.525,-9.41]],"v":[[39.146,-22.694],[-14.96,22.694],[-39.146,22.694],[-39.146,17.527],[-34.669,4.982]],"c":true}},"nm":"Path 1"},{"ty":"fl","c":{"a":0,"k":[0.967,0.773,0.227,1]},"o":{"a":0,"k":100},"r":1,"nm":"Fill 1"},{"ty":"tr","p":{"a":0,"k":[39.421,118.517]},"a":{"a":0,"k":[0,0]},"s":{"a":0,"k":[100,100]},"r":{"a":0,"k":0},"o":{"a":0,"k":100},"sk":{"a":0,"k":0},"sa":{"a":0,"k":0},"nm":"Transform"}],"nm":"Group 12"},{"ty":"gr","it":[{"ind":0,"ty":"sh","ks":{"a":0,"k":{"i":[[-0.462,-10.005],[0,0],[-3.392,8.894],[-38.555,0],[-12.954,-35.099]],"o":[[0,0],[0.308,-10.005],[12.955,-35.099],[38.709,0],[3.394,8.894]],"v":[[90.604,44.311],[-90.604,44.311],[-84.898,15.883],[-0.231,-44.311],[84.743,15.883]],"c":true}},"nm":"Path 1"},{"ty":"fl","c":{"a":0,"k":[0.94,0.912,0.952,1]},"o":{"a":0,"k":100},"r":1,"nm":"Fill 1"},{"ty":"tr","p":{"a":0,"k":[639.117,207.294]},"a":{"a":0,"k":[0,0]},"s":{"a":0,"k":[100,100]},"r":{"a":0,"k":0},"o":{"a":0,"k":100},"sk":{"a":0,"k":0},"sa":{"a":0,"k":0},"nm":"Transform"}],"nm":"Group 13"},{"ty":"gr","it":[{"ind":0,"ty":"sh","ks":{"a":0,"k":{"i":[[-0.462,-10.005],[0,0],[-3.392,8.894],[-38.555,0],[-12.953,-35.099]],"o":[[0,0],[0.308,-10.005],[12.955,-35.099],[38.709,0],[3.394,8.894]],"v":[[90.604,44.311],[-90.604,44.311],[-84.898,15.883],[-0.231,-44.311],[84.743,15.883]],"c":true}},"nm":"Path 1"},{"ty":"fl","c":{"a":0,"k":[0.94,0.912,0.952,1]},"o":{"a":0,"k":100},"r":1,"nm":"Fill 1"},{"ty":"tr","p":{"a":0,"k":[164.899,207.294]},"a":{"a":0,"k":[0,0]},"s":{"a":0,"k":[100,100]},"r":{"a":0,"k":0},"o":{"a":0,"k":100},"sk":{"a":0,"k":0},"sa":{"a":0,"k":0},"nm":"Transform"}],"nm":"Group 14"},{"ty":"gr","it":[{"ind":0,"ty":"sh","ks":{"a":0,"k":{"i":[[0.538,-3.136],[45.148,6.088],[0,-4.797],[0,0],[0,0],[0,4.613],[0,0],[-4.479,-0.553],[-38.698,-17.897]],"o":[[-37.982,-16.42],[-4.658,-0.554],[0,0],[0,0],[-4.479,0.184],[0,0],[0,-4.797],[47.479,6.274],[3.583,1.66]],"v":[[74.263,15.405],[-56.346,-17.065],[-64.947,-9.133],[-64.947,28.321],[-66.737,28.321],[-74.801,20.203],[-74.801,-20.018],[-66.201,-27.953],[69.784,6.919]],"c":true}},"nm":"Path 1"},{"ty":"fl","c":{"a":0,"k":[0.885,0.844,0.916,1]},"o":{"a":0,"k":100},"r":1,"nm":"Fill 1"},{"ty":"tr","p":{"a":0,"k":[591.238,57.539]},"a":{"a":0,"k":[0,0]},"s":{"a":0,"k":[100,100]},"r":{"a":0,"k":0},"o":{"a":0,"k":100},"sk":{"a":0,"k":0},"sa":{"a":0,"k":0},"nm":"Transform"}],"nm":"Group 15"},{"ty":"gr","it":[{"ind":0,"ty":"sh","ks":{"a":0,"k":{"i":[[8.169,-0.369],[0,0],[0,4.541],[0,0],[-4.619,-0.614],[-38.813,-17.916]],"o":[[0,0],[-4.405,0.199],[0,0],[0,-4.796],[47.318,6.296],[7.461,3.444]],"v":[[65.758,22.243],[-67.963,28.289],[-76.044,20.324],[-76.044,-19.955],[-67.346,-27.874],[68.583,6.977]],"c":true}},"nm":"Path 1"},{"ty":"fl","c":{"a":0,"k":[0.94,0.912,0.952,1]},"o":{"a":0,"k":100},"r":1,"nm":"Fill 1"},{"ty":"tr","p":{"a":0,"k":[592.474,57.483]},"a":{"a":0,"k":[0,0]},"s":{"a":0,"k":[100,100]},"r":{"a":0,"k":0},"o":{"a":0,"k":100},"sk":{"a":0,"k":0},"sa":{"a":0,"k":0},"nm":"Transform"}],"nm":"Group 16"},{"ty":"gr","it":[{"ind":0,"ty":"sh","ks":{"a":0,"k":{"i":[[0,-4.06],[0,0],[0.896,0],[20.604,0],[3.404,-3.689],[0,0],[0.358,-0.738],[-4.3,4.429],[0,0],[-5.016,0],[-45.148,-4.243]],"o":[[0,0],[-0.716,-0.185],[-45.149,-4.428],[-5.016,0],[0,0],[-0.538,0.553],[-5.555,-1.292],[0,0],[3.584,-3.69],[20.784,0],[4.122,0.37]],"v":[[91.73,-23.8],[91.73,-20.111],[89.401,-20.664],[-15.946,-25.831],[-29.204,-20.111],[-82.594,34.687],[-84.027,36.716],[-87.431,23.616],[-34.042,-30.996],[-20.784,-36.716],[84.563,-31.735]],"c":true}},"nm":"Path 1"},{"ty":"fl","c":{"a":0,"k":[0.885,0.844,0.916,1]},"o":{"a":0,"k":100},"r":1,"nm":"Fill 1"},{"ty":"tr","p":{"a":0,"k":[406.971,57.447]},"a":{"a":0,"k":[0,0]},"s":{"a":0,"k":[100,100]},"r":{"a":0,"k":0},"o":{"a":0,"k":100},"sk":{"a":0,"k":0},"sa":{"a":0,"k":0},"nm":"Transform"}],"nm":"Group 17"},{"ty":"gr","it":[{"ind":0,"ty":"sh","ks":{"a":0,"k":{"i":[[-4.994,0],[-45.181,-4.327],[0,-4.108],[0,0],[4.14,-0.187],[0,0],[-5.006,5.138],[0,0]],"o":[[20.654,0],[3.972,0.381],[0,0],[0,4.267],[0,0],[-7.061,0.32],[0,0],[3.561,-3.708]],"v":[[-20.341,-37.2],[85.021,-32.116],[92.03,-24.175],[92.03,21.421],[84.626,29.386],[-81.22,36.88],[-87.023,23.269],[-33.658,-31.499]],"c":true}},"nm":"Path 1"},{"ty":"fl","c":{"a":0,"k":[0.94,0.912,0.952,1]},"o":{"a":0,"k":100},"r":1,"nm":"Fill 1"},{"ty":"tr","p":{"a":0,"k":[406.594,57.883]},"a":{"a":0,"k":[0,0]},"s":{"a":0,"k":[100,100]},"r":{"a":0,"k":0},"o":{"a":0,"k":100},"sk":{"a":0,"k":0},"sa":{"a":0,"k":0},"nm":"Transform"}],"nm":"Group 18"},{"ty":"gr","it":[{"ind":0,"ty":"sh","ks":{"a":0,"k":{"i":[[8.169,-0.369],[0,0],[0,4.541],[0,0],[-4.619,-0.614],[-38.813,-17.916]],"o":[[0,0],[-4.405,0.199],[0,0],[0,-4.796],[47.318,6.296],[7.461,3.444]],"v":[[65.758,22.243],[-67.963,28.289],[-76.044,20.324],[-76.044,-19.955],[-67.346,-27.874],[68.583,6.977]],"c":true}},"nm":"Path 1"},{"ty":"fl","c":{"a":0,"k":[0.548,0.453,0.724,1]},"o":{"a":0,"k":100},"r":1,"nm":"Fill 1"},{"ty":"tr","p":{"a":0,"k":[592.474,57.483]},"a":{"a":0,"k":[0,0]},"s":{"a":0,"k":[100,100]},"r":{"a":0,"k":0},"o":{"a":0,"k":100},"sk":{"a":0,"k":0},"sa":{"a":0,"k":0},"nm":"Transform"}],"nm":"Group 19"},{"ty":"gr","it":[{"ind":0,"ty":"sh","ks":{"a":0,"k":{"i":[[-4.994,0],[-45.181,-4.327],[0,-4.108],[0,0],[4.14,-0.187],[0,0],[-5.006,5.138],[0,0]],"o":[[20.654,0],[3.972,0.381],[0,0],[0,4.267],[0,0],[-7.061,0.32],[0,0],[3.561,-3.708]],"v":[[-20.341,-37.2],[85.021,-32.116],[92.03,-24.175],[92.03,21.421],[84.626,29.386],[-81.22,36.88],[-87.023,23.269],[-33.658,-31.499]],"c":true}},"nm":"Path 1"},{"ty":"fl","c":{"a":0,"k":[0.548,0.453,0.724,1]},"o":{"a":0,"k":100},"r":1,"nm":"Fill 1"},{"ty":"tr","p":{"a":0,"k":[406.594,57.883]},"a":{"a":0,"k":[0,0]},"s":{"a":0,"k":[100,100]},"r":{"a":0,"k":0},"o":{"a":0,"k":100},"sk":{"a":0,"k":0},"sa":{"a":0,"k":0},"nm":"Transform"}],"nm":"Group 20"},{"ty":"gr","it":[{"ind":0,"ty":"sh","ks":{"a":0,"k":{"i":[[0,0],[0,0],[6.878,0],[0,0],[5.826,4.154],[0,0],[0,6.54]],"o":[[0,0],[-5.723,3.929],[0,0],[-7.086,0],[0,0],[-5.222,-3.723],[0,0]],"v":[[424.816,-32.327],[339.422,26.301],[320.097,32.327],[-355.227,32.327],[-375.056,25.947],[-416.478,-3.585],[-424.816,-19.973]],"c":true}},"nm":"Path 1"},{"ty":"fl","c":{"a":0,"k":[1,0.333,0.237,1]},"o":{"a":0,"k":100},"r":1,"nm":"Fill 1"},{"ty":"tr","p":{"a":0,"k":[425.067,219.294]},"a":{"a":0,"k":[0,0]},"s":{"a":0,"k":[100,100]},"r":{"a":0,"k":0},"o":{"a":0,"k":100},"sk":{"a":0,"k":0},"sa":{"a":0,"k":0},"nm":"Transform"}],"nm":"Group 21"},{"ty":"gr","it":[{"ind":0,"ty":"sh","ks":{"a":0,"k":{"i":[[0,-2.952],[0,0],[6.451,-4.429],[0,0],[6.808,0],[0,0],[5.733,4.058],[0,0],[0,6.458],[0,0],[-3.046,3.506],[-54.824,0.922],[0,0],[0,0],[-10.212,0],[-81.698,-63.284],[0,0],[-3.046,-12.546]],"o":[[0,0],[0,7.933],[0,0],[-5.733,3.874],[0,0],[-6.987,0],[0,0],[-5.197,-3.691],[0,0],[0,-4.612],[8.062,-10.148],[0,0],[0,0],[7.346,-7.564],[55.541,0.185],[0,0],[13.078,1.292],[0.895,2.583]],"v":[[429.987,-12.73],[429.987,41.145],[419.595,61.071],[334.315,119.743],[314.966,125.647],[-360.474,125.647],[-380.181,119.374],[-421.745,89.854],[-429.987,73.432],[-429.987,10.148],[-425.508,-2.398],[-340.944,-30.442],[-147.45,-35.793],[-71.307,-113.838],[-43.896,-125.647],[277.7,-57.011],[402.038,-44.465],[428.733,-21.033]],"c":true}},"nm":"Path 1"},{"ty":"fl","c":{"a":0,"k":[0.997,0.394,0.343,1]},"o":{"a":0,"k":100},"r":1,"nm":"Fill 1"},{"ty":"tr","p":{"a":0,"k":[430.262,125.897]},"a":{"a":0,"k":[0,0]},"s":{"a":0,"k":[100,100]},"r":{"a":0,"k":0},"o":{"a":0,"k":100},"sk":{"a":0,"k":0},"sa":{"a":0,"k":0},"nm":"Transform"}],"nm":"Group 22"},{"ty":"gr","it":[{"ind":0,"ty":"sh","ks":{"a":0,"k":{"i":[[5.826,4.154],[0,0],[0,6.541],[0,0],[-2.881,3.57],[-54.755,0.932],[0,0],[0,0],[-10.242,-0.012],[-81.677,-63.365],[0,0],[0,-16.415],[0,0],[6.462,-4.436],[0,0],[6.877,0],[0,0]],"o":[[0,0],[-5.222,-3.723],[0,0],[0,-4.641],[8.103,-10.037],[0,0],[0,0],[7.253,-7.446],[55.546,0.065],[0,0],[15.863,1.592],[0,0],[0,7.997],[0,0],[-5.723,3.928],[0,0],[-7.087,0]],"v":[[-380.227,119.269],[-421.65,89.737],[-429.988,73.349],[-429.988,10.139],[-425.561,-2.562],[-340.958,-30.48],[-147.415,-35.795],[-71.24,-114.003],[-43.926,-125.636],[277.734,-57.055],[402.025,-44.581],[429.988,-12.841],[429.988,41.095],[419.645,60.996],[334.251,119.623],[314.927,125.648],[-360.397,125.648]],"c":true}},"nm":"Path 1"},{"ty":"fl","c":{"a":0,"k":[0.997,0.394,0.343,1]},"o":{"a":0,"k":100},"r":1,"nm":"Fill 1"},{"ty":"tr","p":{"a":0,"k":[430.238,125.972]},"a":{"a":0,"k":[0,0]},"s":{"a":0,"k":[100,100]},"r":{"a":0,"k":0},"o":{"a":0,"k":100},"sk":{"a":0,"k":0},"sa":{"a":0,"k":0},"nm":"Transform"}],"nm":"Group 23"}],"ip":0,"op":90,"st":0}]}],"layers":[{"ind":1,"ty":0,"nm":"Pre-comp 1","refId":"comp_0","sr":1,"ks":{"o":{"a":0,"k":100},"r":{"a":0,"k":0},"p":{"a":1,"k":[{"i":{"x":0.833,"y":0.833},"o":{"x":0.167,"y":0.167},"t":0,"s":[1636,500,0],"to":[0,0,0],"ti":[0,0,0]},{"i":{"x":0.667,"y":0.667},"o":{"x":0.167,"y":0.167},"t":30,"s":[500,500,0],"to":[0,0,0],"ti":[0,0,0]},{"i":{"x":0.667,"y":1},"o":{"x":0.333,"y":0},"t":32,"s":[500,500,0],"to":[0,0,0],"ti":[0,0,0]},{"i":{"x":0.667,"y":1},"o":{"x":0.333,"y":0},"t":45.154,"s":[500,476,0],"to":[0,0,0],"ti":[0,0,0]},{"i":{"x":0.667,"y":1},"o":{"x":0.333,"y":0},"t":53.923,"s":[492,524,0],"to":[0,0,0],"ti":[0,0,0]},{"i":{"x":0.667,"y":1},"o":{"x":0.333,"y":0},"t":67.078,"s":[472,512,0],"to":[0,0,0],"ti":[0,0,0]},{"t":89,"s":[500,500,0]}],"l":2},"a":{"a":0,"k":[500,500,0],"l":2},"s":{"a":0,"k":[100,100,100],"l":2}},"ao":0,"w":1000,"h":1000,"ip":0,"op":90,"st":0}],"markers":[]}